scyjava/__init__.py
scyjava/_arrays.py
scyjava/_cjdk_fetch.py
scyjava/_convert.py
scyjava/_introspect.py
scyjava/_jvm.py
scyjava/_script.py
scyjava/_types.py
scyjava/_versions.py
scyjava/config.py
scyjava/inspect.py
scyjava-1.12.0.dist-info/METADATA
scyjava-1.12.0.dist-info/WHEEL
scyjava-1.12.0.dist-info/top_level.txt
scyjava-1.12.0.dist-info/RECORD
