Metadata-Version: 2.4
Name: scyjava
Version: 1.12.0
Summary: Supercharged Java access from Python
Author-email: SciJava developers <ctrueden@wisc.edu>
License-Expression: Unlicense
Project-URL: homepage, https://github.com/scijava/scyjava
Project-URL: documentation, https://github.com/scijava/scyjava/blob/main/README.md
Project-URL: source, https://github.com/scijava/scyjava
Project-URL: download, https://pypi.org/project/scyjava/
Project-URL: tracker, https://github.com/scijava/scyjava/issues
Keywords: java,maven,cross-language
Classifier: Development Status :: 5 - Production/Stable
Classifier: Intended Audience :: Developers
Classifier: Intended Audience :: Education
Classifier: Intended Audience :: Science/Research
Classifier: Programming Language :: Python :: 3 :: Only
Classifier: Programming Language :: Python :: 3.9
Classifier: Programming Language :: Python :: 3.10
Classifier: Programming Language :: Python :: 3.11
Classifier: Programming Language :: Python :: 3.12
Classifier: Programming Language :: Python :: 3.13
Classifier: Operating System :: Microsoft :: Windows
Classifier: Operating System :: Unix
Classifier: Operating System :: MacOS
Classifier: Topic :: Scientific/Engineering
Classifier: Topic :: Software Development :: Libraries :: Java Libraries
Classifier: Topic :: Software Development :: Libraries :: Python Modules
Classifier: Topic :: Utilities
Requires-Python: >=3.9
Requires-Dist: jpype1>=1.3.0
Requires-Dist: jgo
Requires-Dist: cjdk
Provides-Extra: dev
Requires-Dist: assertpy; extra == "dev"
Requires-Dist: build; extra == "dev"
Requires-Dist: jep; extra == "dev"
Requires-Dist: pytest; extra == "dev"
Requires-Dist: pytest-cov; extra == "dev"
Requires-Dist: numpy; extra == "dev"
Requires-Dist: pandas; extra == "dev"
Requires-Dist: ruff; extra == "dev"
Requires-Dist: toml; extra == "dev"
Requires-Dist: validate-pyproject[all]; extra == "dev"
